{
  "id": "00000000-0000-0000-0000-000000000000",
  "prevId": "",
  "version": "5",
  "dialect": "pg",
  "tables": {
    "character": {
      "name": "character",
      "schema": "",
      "columns": {
        "id": {
          "name": "id",
          "type": "serial",
          "primaryKey": true,
          "notNull": true
        },
        "user_id": {
          "name": "user_id",
          "type": "text",
          "primaryKey": false,
          "notNull": false
        },
        "char_id": {
          "name": "char_id",
          "type": "integer",
          "primaryKey": false,
          "notNull": false
        },
        "is_active_character": {
          "name": "is_active_character",
          "type": "boolean",
          "primaryKey": false,
          "notNull": false,
          "default": true
        },
        "character_data": {
          "name": "character_data",
          "type": "jsonb",
          "primaryKey": false,
          "notNull": false,
          "default": "'{}'::jsonb"
        },
        "calculated_stats": {
          "name": "calculated_stats",
          "type": "jsonb",
          "primaryKey": false,
          "notNull": false,
          "default": "'{}'::jsonb"
        },
        "created_at": {
          "name": "created_at",
          "type": "timestamp with time zone",
          "primaryKey": false,
          "notNull": false,
          "default": "CURRENT_TIMESTAMP"
        },
        "last_updated_at": {
          "name": "last_updated_at",
          "type": "timestamp with time zone",
          "primaryKey": false,
          "notNull": false,
          "default": "CURRENT_TIMESTAMP"
        },
        "attributes": {
          "name": "attributes",
          "type": "jsonb",
          "primaryKey": false,
          "notNull": true,
          "default": "'[]'::jsonb"
        },
        "custom_attributes": {
          "name": "custom_attributes",
          "type": "jsonb",
          "primaryKey": false,
          "notNull": true,
          "default": "'[]'::jsonb"
        },
        "modifiers": {
          "name": "modifiers",
          "type": "jsonb",
          "primaryKey": false,
          "notNull": true,
          "default": "'[]'::jsonb"
        },
        "actions": {
          "name": "actions",
          "type": "jsonb",
          "primaryKey": false,
          "notNull": true,
          "default": "'[]'::jsonb"
        },
        "custom_actions": {
          "name": "custom_actions",
          "type": "jsonb",
          "primaryKey": false,
          "notNull": true,
          "default": "'[]'::jsonb"
        },
        "roll_macros": {
          "name": "roll_macros",
          "type": "jsonb",
          "primaryKey": false,
          "notNull": true,
          "default": "'[]'::jsonb"
        },
        "import_source": {
          "name": "import_source",
          "type": "varchar(255)",
          "primaryKey": false,
          "notNull": false,
          "default": "'wg'::character varying"
        },
        "sheet": {
          "name": "sheet",
          "type": "jsonb",
          "primaryKey": false,
          "notNull": false,
          "default": "'{}'::jsonb"
        },
        "name": {
          "name": "name",
          "type": "varchar(255)",
          "primaryKey": false,
          "notNull": false
        },
        "tracker_message_id": {
          "name": "tracker_message_id",
          "type": "varchar(255)",
          "primaryKey": false,
          "notNull": false,
          "default": "NULL::character varying"
        },
        "tracker_channel_id": {
          "name": "tracker_channel_id",
          "type": "varchar(255)",
          "primaryKey": false,
          "notNull": false,
          "default": "NULL::character varying"
        },
        "tracker_guild_id": {
          "name": "tracker_guild_id",
          "type": "varchar(255)",
          "primaryKey": false,
          "notNull": false,
          "default": "NULL::character varying"
        },
        "tracker_mode": {
          "name": "tracker_mode",
          "type": "text",
          "primaryKey": false,
          "notNull": false,
          "default": "'counters_only'"
        }
      },
      "indexes": {},
      "foreignKeys": {},
      "compositePrimaryKeys": {},
      "uniqueConstraints": {}
    },
    "game": {
      "name": "game",
      "schema": "",
      "columns": {
        "id": {
          "name": "id",
          "type": "serial",
          "primaryKey": true,
          "notNull": true
        },
        "gm_user_id": {
          "name": "gm_user_id",
          "type": "text",
          "primaryKey": false,
          "notNull": true
        },
        "name": {
          "name": "name",
          "type": "text",
          "primaryKey": false,
          "notNull": false
        },
        "guild_id": {
          "name": "guild_id",
          "type": "text",
          "primaryKey": false,
          "notNull": true
        },
        "is_active": {
          "name": "is_active",
          "type": "boolean",
          "primaryKey": false,
          "notNull": true,
          "default": false
        },
        "created_at": {
          "name": "created_at",
          "type": "timestamp with time zone",
          "primaryKey": false,
          "notNull": false,
          "default": "CURRENT_TIMESTAMP"
        },
        "last_updated_at": {
          "name": "last_updated_at",
          "type": "timestamp with time zone",
          "primaryKey": false,
          "notNull": false,
          "default": "CURRENT_TIMESTAMP"
        }
      },
      "indexes": {},
      "foreignKeys": {},
      "compositePrimaryKeys": {},
      "uniqueConstraints": {
        "game_name_guild_id_unique": {
          "columns": [
            "name",
            "guild_id"
          ],
          "nullsNotDistinct": false,
          "name": "game_name_guild_id_unique"
        }
      }
    },
    "knex_migrations": {
      "name": "knex_migrations",
      "schema": "",
      "columns": {
        "id": {
          "name": "id",
          "type": "serial",
          "primaryKey": true,
          "notNull": true
        },
        "name": {
          "name": "name",
          "type": "varchar(255)",
          "primaryKey": false,
          "notNull": false
        },
        "batch": {
          "name": "batch",
          "type": "integer",
          "primaryKey": false,
          "notNull": false
        },
        "migration_time": {
          "name": "migration_time",
          "type": "timestamp with time zone",
          "primaryKey": false,
          "notNull": false
        }
      },
      "indexes": {},
      "foreignKeys": {},
      "compositePrimaryKeys": {},
      "uniqueConstraints": {}
    },
    "knex_migrations_lock": {
      "name": "knex_migrations_lock",
      "schema": "",
      "columns": {
        "index": {
          "name": "index",
          "type": "serial",
          "primaryKey": true,
          "notNull": true
        },
        "is_locked": {
          "name": "is_locked",
          "type": "integer",
          "primaryKey": false,
          "notNull": false
        }
      },
      "indexes": {},
      "foreignKeys": {},
      "compositePrimaryKeys": {},
      "uniqueConstraints": {}
    },
    "user_settings": {
      "name": "user_settings",
      "schema": "",
      "columns": {
        "user_id": {
          "name": "user_id",
          "type": "varchar(255)",
          "primaryKey": true,
          "notNull": true
        },
        "init_stats_notification": {
          "name": "init_stats_notification",
          "type": "text",
          "primaryKey": false,
          "notNull": false,
          "default": "'whenever_hidden'"
        },
        "roll_compact_mode": {
          "name": "roll_compact_mode",
          "type": "text",
          "primaryKey": false,
          "notNull": false,
          "default": "'normal'"
        },
        "inline_rolls_display": {
          "name": "inline_rolls_display",
          "type": "text",
          "primaryKey": false,
          "notNull": false,
          "default": "'detailed'"
        }
      },
      "indexes": {},
      "foreignKeys": {},
      "compositePrimaryKeys": {},
      "uniqueConstraints": {}
    },
    "wg_auth_token": {
      "name": "wg_auth_token",
      "schema": "",
      "columns": {
        "id": {
          "name": "id",
          "type": "serial",
          "primaryKey": true,
          "notNull": true
        },
        "char_id": {
          "name": "char_id",
          "type": "integer",
          "primaryKey": false,
          "notNull": true
        },
        "access_token": {
          "name": "access_token",
          "type": "text",
          "primaryKey": false,
          "notNull": true
        },
        "expires_at": {
          "name": "expires_at",
          "type": "timestamp",
          "primaryKey": false,
          "notNull": true
        },
        "access_rights": {
          "name": "access_rights",
          "type": "text",
          "primaryKey": false,
          "notNull": true
        },
        "token_type": {
          "name": "token_type",
          "type": "text",
          "primaryKey": false,
          "notNull": true
        }
      },
      "indexes": {},
      "foreignKeys": {},
      "compositePrimaryKeys": {},
      "uniqueConstraints": {}
    },
    "bestiary_files_loaded": {
      "name": "bestiary_files_loaded",
      "schema": "",
      "columns": {
        "id": {
          "name": "id",
          "type": "serial",
          "primaryKey": true,
          "notNull": true
        },
        "file_name": {
          "name": "file_name",
          "type": "text",
          "primaryKey": false,
          "notNull": false
        },
        "file_hash": {
          "name": "file_hash",
          "type": "text",
          "primaryKey": false,
          "notNull": false
        },
        "created_at": {
          "name": "created_at",
          "type": "timestamp with time zone",
          "primaryKey": false,
          "notNull": false,
          "default": "CURRENT_TIMESTAMP"
        },
        "last_updated_at": {
          "name": "last_updated_at",
          "type": "timestamp with time zone",
          "primaryKey": false,
          "notNull": false,
          "default": "CURRENT_TIMESTAMP"
        }
      },
      "indexes": {},
      "foreignKeys": {},
      "compositePrimaryKeys": {},
      "uniqueConstraints": {}
    },
    "characters_in_games": {
      "name": "characters_in_games",
      "schema": "",
      "columns": {
        "game_id": {
          "name": "game_id",
          "type": "integer",
          "primaryKey": false,
          "notNull": true
        },
        "character_id": {
          "name": "character_id",
          "type": "integer",
          "primaryKey": false,
          "notNull": true
        },
        "created_at": {
          "name": "created_at",
          "type": "timestamp with time zone",
          "primaryKey": false,
          "notNull": false,
          "default": "CURRENT_TIMESTAMP"
        },
        "last_updated_at": {
          "name": "last_updated_at",
          "type": "timestamp with time zone",
          "primaryKey": false,
          "notNull": false,
          "default": "CURRENT_TIMESTAMP"
        }
      },
      "indexes": {},
      "foreignKeys": {
        "characters_in_games_character_id_foreign": {
          "name": "characters_in_games_character_id_foreign",
          "tableFrom": "characters_in_games",
          "tableTo": "character",
          "columnsFrom": [
            "character_id"
          ],
          "columnsTo": [
            "id"
          ],
          "onDelete": "cascade",
          "onUpdate": "no action"
        },
        "characters_in_games_game_id_foreign": {
          "name": "characters_in_games_game_id_foreign",
          "tableFrom": "characters_in_games",
          "tableTo": "game",
          "columnsFrom": [
            "game_id"
          ],
          "columnsTo": [
            "id"
          ],
          "onDelete": "cascade",
          "onUpdate": "no action"
        }
      },
      "compositePrimaryKeys": {},
      "uniqueConstraints": {}
    },
    "initiative": {
      "name": "initiative",
      "schema": "",
      "columns": {
        "id": {
          "name": "id",
          "type": "serial",
          "primaryKey": true,
          "notNull": true
        },
        "channel_id": {
          "name": "channel_id",
          "type": "text",
          "primaryKey": false,
          "notNull": true
        },
        "gm_user_id": {
          "name": "gm_user_id",
          "type": "text",
          "primaryKey": false,
          "notNull": true
        },
        "round_message_ids": {
          "name": "round_message_ids",
          "type": "jsonb",
          "primaryKey": false,
          "notNull": false
        },
        "current_round": {
          "name": "current_round",
          "type": "integer",
          "primaryKey": false,
          "notNull": true,
          "default": 0
        },
        "current_turn_group_id": {
          "name": "current_turn_group_id",
          "type": "integer",
          "primaryKey": false,
          "notNull": false
        },
        "created_at": {
          "name": "created_at",
          "type": "timestamp with time zone",
          "primaryKey": false,
          "notNull": false,
          "default": "CURRENT_TIMESTAMP"
        },
        "last_updated_at": {
          "name": "last_updated_at",
          "type": "timestamp with time zone",
          "primaryKey": false,
          "notNull": false,
          "default": "CURRENT_TIMESTAMP"
        }
      },
      "indexes": {},
      "foreignKeys": {},
      "compositePrimaryKeys": {},
      "uniqueConstraints": {
        "initiative_channel_id_unique": {
          "columns": [
            "channel_id"
          ],
          "nullsNotDistinct": false,
          "name": "initiative_channel_id_unique"
        }
      }
    },
    "initiative_actor": {
      "name": "initiative_actor",
      "schema": "",
      "columns": {
        "id": {
          "name": "id",
          "type": "serial",
          "primaryKey": true,
          "notNull": true
        },
        "initiative_id": {
          "name": "initiative_id",
          "type": "integer",
          "primaryKey": false,
          "notNull": true
        },
        "initiative_actor_group_id": {
          "name": "initiative_actor_group_id",
          "type": "integer",
          "primaryKey": false,
          "notNull": true
        },
        "character_id": {
          "name": "character_id",
          "type": "integer",
          "primaryKey": false,
          "notNull": false
        },
        "user_id": {
          "name": "user_id",
          "type": "text",
          "primaryKey": false,
          "notNull": true
        },
        "name": {
          "name": "name",
          "type": "text",
          "primaryKey": false,
          "notNull": true
        },
        "created_at": {
          "name": "created_at",
          "type": "timestamp with time zone",
          "primaryKey": false,
          "notNull": false,
          "default": "CURRENT_TIMESTAMP"
        },
        "last_updated_at": {
          "name": "last_updated_at",
          "type": "timestamp with time zone",
          "primaryKey": false,
          "notNull": false,
          "default": "CURRENT_TIMESTAMP"
        },
        "sheet": {
          "name": "sheet",
          "type": "jsonb",
          "primaryKey": false,
          "notNull": false,
          "default": "'{}'::jsonb"
        },
        "reference_npc_name": {
          "name": "reference_npc_name",
          "type": "text",
          "primaryKey": false,
          "notNull": false
        },
        "hide_stats": {
          "name": "hide_stats",
          "type": "boolean",
          "primaryKey": false,
          "notNull": true,
          "default": false
        }
      },
      "indexes": {},
      "foreignKeys": {
        "initiative_actor_character_id_foreign": {
          "name": "initiative_actor_character_id_foreign",
          "tableFrom": "initiative_actor",
          "tableTo": "character",
          "columnsFrom": [
            "character_id"
          ],
          "columnsTo": [
            "id"
          ],
          "onDelete": "set null",
          "onUpdate": "no action"
        },
        "initiative_actor_initiative_actor_group_id_foreign": {
          "name": "initiative_actor_initiative_actor_group_id_foreign",
          "tableFrom": "initiative_actor",
          "tableTo": "initiative_actor_group",
          "columnsFrom": [
            "initiative_actor_group_id"
          ],
          "columnsTo": [
            "id"
          ],
          "onDelete": "cascade",
          "onUpdate": "no action"
        },
        "initiative_actor_initiative_id_foreign": {
          "name": "initiative_actor_initiative_id_foreign",
          "tableFrom": "initiative_actor",
          "tableTo": "initiative",
          "columnsFrom": [
            "initiative_id"
          ],
          "columnsTo": [
            "id"
          ],
          "onDelete": "cascade",
          "onUpdate": "no action"
        }
      },
      "compositePrimaryKeys": {},
      "uniqueConstraints": {}
    },
    "initiative_actor_group": {
      "name": "initiative_actor_group",
      "schema": "",
      "columns": {
        "id": {
          "name": "id",
          "type": "serial",
          "primaryKey": true,
          "notNull": true
        },
        "initiative_id": {
          "name": "initiative_id",
          "type": "integer",
          "primaryKey": false,
          "notNull": true
        },
        "user_id": {
          "name": "user_id",
          "type": "text",
          "primaryKey": false,
          "notNull": true
        },
        "name": {
          "name": "name",
          "type": "text",
          "primaryKey": false,
          "notNull": true
        },
        "initiative_result": {
          "name": "initiative_result",
          "type": "numeric(8, 2)",
          "primaryKey": false,
          "notNull": true
        },
        "created_at": {
          "name": "created_at",
          "type": "timestamp with time zone",
          "primaryKey": false,
          "notNull": false,
          "default": "CURRENT_TIMESTAMP"
        },
        "last_updated_at": {
          "name": "last_updated_at",
          "type": "timestamp with time zone",
          "primaryKey": false,
          "notNull": false,
          "default": "CURRENT_TIMESTAMP"
        }
      },
      "indexes": {},
      "foreignKeys": {
        "initiative_actor_group_initiative_id_foreign": {
          "name": "initiative_actor_group_initiative_id_foreign",
          "tableFrom": "initiative_actor_group",
          "tableTo": "initiative",
          "columnsFrom": [
            "initiative_id"
          ],
          "columnsTo": [
            "id"
          ],
          "onDelete": "cascade",
          "onUpdate": "no action"
        }
      },
      "compositePrimaryKeys": {},
      "uniqueConstraints": {}
    },
    "npc": {
      "name": "npc",
      "schema": "",
      "columns": {
        "id": {
          "name": "id",
          "type": "serial",
          "primaryKey": true,
          "notNull": true
        },
        "data": {
          "name": "data",
          "type": "jsonb",
          "primaryKey": false,
          "notNull": false,
          "default": "'{}'::jsonb"
        },
        "fluff": {
          "name": "fluff",
          "type": "jsonb",
          "primaryKey": false,
          "notNull": false,
          "default": "'{}'::jsonb"
        },
        "name": {
          "name": "name",
          "type": "text",
          "primaryKey": false,
          "notNull": false
        },
        "source_file_name": {
          "name": "source_file_name",
          "type": "text",
          "primaryKey": false,
          "notNull": false
        },
        "created_at": {
          "name": "created_at",
          "type": "timestamp with time zone",
          "primaryKey": false,
          "notNull": false,
          "default": "CURRENT_TIMESTAMP"
        },
        "last_updated_at": {
          "name": "last_updated_at",
          "type": "timestamp with time zone",
          "primaryKey": false,
          "notNull": false,
          "default": "CURRENT_TIMESTAMP"
        }
      },
      "indexes": {
        "npc_name_index": {
          "name": "npc_name_index",
          "columns": [
            "name"
          ],
          "isUnique": false
        },
        "source_file_name_index": {
          "name": "source_file_name_index",
          "columns": [
            "source_file_name"
          ],
          "isUnique": false
        }
      },
      "foreignKeys": {},
      "compositePrimaryKeys": {},
      "uniqueConstraints": {}
    },
    "channel_default_character": {
      "name": "channel_default_character",
      "schema": "",
      "columns": {
        "user_id": {
          "name": "user_id",
          "type": "varchar(255)",
          "primaryKey": false,
          "notNull": true
        },
        "character_id": {
          "name": "character_id",
          "type": "integer",
          "primaryKey": false,
          "notNull": true
        },
        "channel_id": {
          "name": "channel_id",
          "type": "varchar(255)",
          "primaryKey": false,
          "notNull": true
        }
      },
      "indexes": {},
      "foreignKeys": {
        "channel_default_character_character_id_foreign": {
          "name": "channel_default_character_character_id_foreign",
          "tableFrom": "channel_default_character",
          "tableTo": "character",
          "columnsFrom": [
            "character_id"
          ],
          "columnsTo": [
            "id"
          ],
          "onDelete": "cascade",
          "onUpdate": "no action"
        }
      },
      "compositePrimaryKeys": {
        "channel_default_character_user_id_channel_id": {
          "name": "channel_default_character_pkey",
          "columns": [
            "user_id",
            "channel_id"
          ]
        }
      },
      "uniqueConstraints": {}
    },
    "guild_default_character": {
      "name": "guild_default_character",
      "schema": "",
      "columns": {
        "user_id": {
          "name": "user_id",
          "type": "varchar(255)",
          "primaryKey": false,
          "notNull": true
        },
        "character_id": {
          "name": "character_id",
          "type": "integer",
          "primaryKey": false,
          "notNull": true
        },
        "guild_id": {
          "name": "guild_id",
          "type": "varchar(255)",
          "primaryKey": false,
          "notNull": true
        }
      },
      "indexes": {},
      "foreignKeys": {
        "guild_default_character_character_id_foreign": {
          "name": "guild_default_character_character_id_foreign",
          "tableFrom": "guild_default_character",
          "tableTo": "character",
          "columnsFrom": [
            "character_id"
          ],
          "columnsTo": [
            "id"
          ],
          "onDelete": "cascade",
          "onUpdate": "no action"
        }
      },
      "compositePrimaryKeys": {
        "guild_default_character_user_id_guild_id": {
          "name": "guild_default_character_pkey",
          "columns": [
            "user_id",
            "guild_id"
          ]
        }
      },
      "uniqueConstraints": {}
    }
  },
  "enums": {
    "key_status": {
      "name": "key_status",
      "values": {
        "default": "default",
        "valid": "valid",
        "invalid": "invalid",
        "expired": "expired"
      }
    },
    "key_type": {
      "name": "key_type",
      "values": {
        "aead-ietf": "aead-ietf",
        "aead-det": "aead-det",
        "hmacsha512": "hmacsha512",
        "hmacsha256": "hmacsha256",
        "auth": "auth",
        "shorthash": "shorthash",
        "generichash": "generichash",
        "kdf": "kdf",
        "secretbox": "secretbox",
        "secretstream": "secretstream",
        "stream_xchacha20": "stream_xchacha20"
      }
    },
    "aal_level": {
      "name": "aal_level",
      "values": {
        "aal1": "aal1",
        "aal2": "aal2",
        "aal3": "aal3"
      }
    },
    "code_challenge_method": {
      "name": "code_challenge_method",
      "values": {
        "s256": "s256",
        "plain": "plain"
      }
    },
    "factor_status": {
      "name": "factor_status",
      "values": {
        "unverified": "unverified",
        "verified": "verified"
      }
    },
    "factor_type": {
      "name": "factor_type",
      "values": {
        "totp": "totp",
        "webauthn": "webauthn"
      }
    }
  },
  "schemas": {},
  "_meta": {
    "schemas": {},
    "tables": {},
    "columns": {}
  }
}